sslclient/__init__.py
sslclient/messages_robocup_ssl_detection_pb2.py
sslclient/messages_robocup_ssl_geometry_legacy_pb2.py
sslclient/messages_robocup_ssl_geometry_pb2.py
sslclient/messages_robocup_ssl_refbox_log_pb2.py
sslclient/messages_robocup_ssl_wrapper_legacy_pb2.py
sslclient/messages_robocup_ssl_wrapper_pb2.py
sslclient/sslclient.py
sslclient-1.1.2.dist-info/LICENSE.txt
sslclient-1.1.2.dist-info/METADATA
sslclient-1.1.2.dist-info/WHEEL
sslclient-1.1.2.dist-info/top_level.txt
sslclient-1.1.2.dist-info/RECORD
