Metadata-Version: 2.1
Name: sslclient
Version: 1.1.2
Summary: SSLVision client API in python
Home-page: https://github.com/juniorlimaivd/python-ssl-vision
Author: Junior Lima
Author-email: junior.lima.ivd.2@gmail.com
License: UNKNOWN
Platform: UNKNOWN
Classifier: Programming Language :: Python
Classifier: Programming Language :: Python :: 2
Classifier: Programming Language :: Python :: 2.7
Classifier: License :: OSI Approved :: MIT License
Classifier: Operating System :: OS Independent
Requires-Dist: protobuf
Requires-Dist: wheel
